glutil/__init__.py
glutil/cli.py
glutil/database_cleaner.py
glutil/partitioner.py
glutil/serverless_function.py
glutil/utils.py
glutil/text/__init__.py
glutil/text/cli_text.py
glutil-1.0.0.dist-info/LICENSE
glutil-1.0.0.dist-info/METADATA
glutil-1.0.0.dist-info/WHEEL
glutil-1.0.0.dist-info/entry_points.txt
glutil-1.0.0.dist-info/top_level.txt
glutil-1.0.0.dist-info/RECORD
