Metadata-Version: 2.1
Name: glutil
Version: 1.0.0
Summary: A collection of utilities for managing AWS Glue Data Catalog tables backed by S3
Home-page: https://github.com/Journera/glutil
Author: Journera Inc
Author-email: opensource@journera.com
License: BSD
Platform: UNKNOWN
Classifier: License :: OSI Approved :: BSD License
Classifier: Programming Language :: Python
Classifier: Programming Language :: Python :: 3
Classifier: Programming Language :: Python :: Implementation :: CPython
Classifier: Programming Language :: Python :: Implementation :: PyPy
Classifier: Intended Audience :: System Administrators
Requires-Python: >=3.6.0
Requires-Dist: boto3 (>=1.9)
